<?xml version="1.0" encoding="utf-8" ?><dwsync><file name="agent_setting.php" server="emancipatic.org" local="3619769073" remote="321314310988777492" Dst="-1" /><file name="class-ticket-form.php" server="emancipatic.org" local="3619769073" remote="321314310988777492" Dst="-1" /><file name="class-ticket-operations.php" server="emancipatic.org" local="3619769073" remote="321314310988777492" Dst="-1" /><file name="dashboard.php" server="emancipatic.org" local="3619769073" remote="321314310988777492" Dst="-1" /><file name="create-ticket-back.php" server="emancipatic.org" local="3619768115" remote="321314310988242832" Dst="-1" /><file name="create-ticket.php" server="emancipatic.org" local="3619769073" remote="321314310988777492" Dst="-1" /><file name="guest.php" server="emancipatic.org" local="3619769074" remote="321314310988777492" Dst="-1" /><file name="logged-in.php" server="emancipatic.org" local="3619769074" remote="321314310988777492" Dst="-1" /><file name="ticket-list.php" server="emancipatic.org" local="3619769079" remote="321314310988777492" Dst="-1" /><file name="tickets.php" server="emancipatic.org" local="3619769080" remote="321314310988777492" Dst="-1" /></dwsync>